py2gsuite/__init__.py
py2gsuite/api/__init__.py
py2gsuite/api/base.py
py2gsuite/api/sheets.py
py2gsuite/api/slides.py
py2gsuite/utils/__init__.py
py2gsuite/utils/credential.py
py2gsuite/utils/format.py
py2gsuite/utils/logger.py
py2gsuite/utils/types.py
py2gsuite-0.2.0.dist-info/LICENSE
py2gsuite-0.2.0.dist-info/WHEEL
py2gsuite-0.2.0.dist-info/METADATA
py2gsuite-0.2.0.dist-info/RECORD
