Metadata-Version: 2.1
Name: py2gsuite
Version: 0.2.0
Summary: 
Author: ktro2828
Author-email: kotaro.uetake@tier4.jp
Requires-Python: >=3.8,<4.0
Classifier: Programming Language :: Python :: 3
Classifier: Programming Language :: Python :: 3.10
Classifier: Programming Language :: Python :: 3.8
Classifier: Programming Language :: Python :: 3.9
Requires-Dist: coloredlogs (>=15.0.1,<16.0.0)
Requires-Dist: google-api-python-client (>=2.52.0,<3.0.0)
Requires-Dist: google-auth-httplib2 (>=0.1.0,<0.2.0)
Requires-Dist: google-auth-oauthlib (>=0.5.2,<0.6.0)
